sf2/__init__.py
sf2/__main__.py
sf2/args.py
sf2/auth_sign.py
sf2/cipher.py
sf2/container_base.py
sf2/container_ssh.py
sf2/convert_container.py
sf2/core.py
sf2/core_with_environment.py
sf2/fernetramfile.py
sf2/file_object.py
sf2/json_support.py
sf2/msgpack_support.py
sf2/openinram.py
sf2/sf2.py
sf2/ssh_file_object.py
sf2/gui/__init__.py
sf2/gui/about.py
sf2/gui/change_password.py
sf2/gui/convert.py
sf2/gui/decrypt.py
sf2/gui/encrypt.py
sf2/gui/gui.py
sf2/gui/new.py
sf2/gui/open.py
sf2/gui/ssh.py
sf2/gui/tools.py
sf2/gui/verify.py
sf2-2.0.0.dist-info/LICENSE
sf2-2.0.0.dist-info/METADATA
sf2-2.0.0.dist-info/WHEEL
sf2-2.0.0.dist-info/entry_points.txt
sf2-2.0.0.dist-info/top_level.txt
sf2-2.0.0.dist-info/RECORD
