Metadata-Version: 2.1
Name: sf2
Version: 2.0.0
Summary: Share and work in team your files in full safety thanks to SSH keys.
Home-page: https://github.com/laulin/sf2
Author: Laurent MOULIN
Author-email: gignops@gmail.com
License: MIT
Platform: UNKNOWN
Classifier: Programming Language :: Python :: 3
Classifier: License :: OSI Approved :: MIT License
Classifier: Operating System :: OS Independent
Classifier: Development Status :: 5 - Production/Stable
Classifier: Intended Audience :: Information Technology
Classifier: Topic :: Security :: Cryptography
Requires-Python: >=3
Requires-Dist: cryptography
Requires-Dist: flufl.lock
Requires-Dist: inotify
Requires-Dist: msgpack
Requires-Dist: password-validator
Requires-Dist: pywebio
Requires-Dist: pywebview
Requires-Dist: pyyaml
